WuaiPojieWoShiYonghuPojieShizhan/README.md
WuaiPojieWoShiYonghuPojieShizhan/__init__.py
WuaiPojieWoShiYonghuPojieShizhan/__main__.py
WuaiPojieWoShiYonghuPojieShizhan/file.epub
WuaiPojieWoShiYonghuPojieShizhan/index.html
WuaiPojieWoShiYonghuPojieShizhan/css/__init__.py
WuaiPojieWoShiYonghuPojieShizhan/css/annotations.css
WuaiPojieWoShiYonghuPojieShizhan/css/main.css
WuaiPojieWoShiYonghuPojieShizhan/css/normalize.css
WuaiPojieWoShiYonghuPojieShizhan/css/popup.css
WuaiPojieWoShiYonghuPojieShizhan/font/__init__.py
WuaiPojieWoShiYonghuPojieShizhan/font/fontello.eot
WuaiPojieWoShiYonghuPojieShizhan/font/fontello.svg
WuaiPojieWoShiYonghuPojieShizhan/font/fontello.ttf
WuaiPojieWoShiYonghuPojieShizhan/font/fontello.woff
WuaiPojieWoShiYonghuPojieShizhan/img/__init__.py
WuaiPojieWoShiYonghuPojieShizhan/img/annotator-glyph-sprite.png
WuaiPojieWoShiYonghuPojieShizhan/img/annotator-icon-sprite.png
WuaiPojieWoShiYonghuPojieShizhan/img/apple-touch-icon.png
WuaiPojieWoShiYonghuPojieShizhan/img/cancelfullscreen.png
WuaiPojieWoShiYonghuPojieShizhan/img/close.png
WuaiPojieWoShiYonghuPojieShizhan/img/fullscreen.png
WuaiPojieWoShiYonghuPojieShizhan/img/loader.gif
WuaiPojieWoShiYonghuPojieShizhan/img/menu-icon.png
WuaiPojieWoShiYonghuPojieShizhan/img/save.png
WuaiPojieWoShiYonghuPojieShizhan/img/saved.png
WuaiPojieWoShiYonghuPojieShizhan/img/settings-s.png
WuaiPojieWoShiYonghuPojieShizhan/img/settings.png
WuaiPojieWoShiYonghuPojieShizhan/img/star.png
WuaiPojieWoShiYonghuPojieShizhan/js/__init__.py
WuaiPojieWoShiYonghuPojieShizhan/js/epub.js
WuaiPojieWoShiYonghuPojieShizhan/js/epub.min.js
WuaiPojieWoShiYonghuPojieShizhan/js/epub.min.map
WuaiPojieWoShiYonghuPojieShizhan/js/hooks.min.js
WuaiPojieWoShiYonghuPojieShizhan/js/hooks.min.map
WuaiPojieWoShiYonghuPojieShizhan/js/reader.js
WuaiPojieWoShiYonghuPojieShizhan/js/reader.js.map
WuaiPojieWoShiYonghuPojieShizhan/js/reader.min.js
WuaiPojieWoShiYonghuPojieShizhan/js/reader.min.map
WuaiPojieWoShiYonghuPojieShizhan/js/hooks/__init__.py
wuai_pojie_wo_shi_yonghu_pojie_shizhan-2024.3.2.0.dist-info/METADATA
wuai_pojie_wo_shi_yonghu_pojie_shizhan-2024.3.2.0.dist-info/WHEEL
wuai_pojie_wo_shi_yonghu_pojie_shizhan-2024.3.2.0.dist-info/entry_points.txt
wuai_pojie_wo_shi_yonghu_pojie_shizhan-2024.3.2.0.dist-info/top_level.txt
wuai_pojie_wo_shi_yonghu_pojie_shizhan-2024.3.2.0.dist-info/RECORD
